Workbook

Sheet README
A1: REEF RUN — Kickstarter funding model
A2: Built 2026-10-17 by tools/build_funding_model.py. Campaign currency: EUR (creator resident in the Netherlands). Costs quoted in USD (Steam fee, US entity) are converted with the FX input.
A4: COLOUR LEGEND
A5: Blue text = an input you may edit. Yellow fill = a key assumption that is NOT verified — check it first. Black = formula (do not overwrite). Green = pulled from another sheet.
A7: HOW TO USE
A8: 1. Inputs: platform fees (verified 2026-10-17, kickstarter.com/help/fees), FX, drop rate, tax reserve, entity route, conversion rates.
A9: 2. Labor: remaining work packages in hours per scenario (MVD / Realistic / Expanded). Edit hours as the team re-estimates.
A10: 3. Costs: every non-labor cash cost per scenario, with source or reasoning. Founder labor is NOT here — it is on Scenarios as stipend (cash) and as unpaid value (not cash).
A11: 4. Rewards: tier prices, expected mix of backers, fulfilment cost and fees → blended average pledge and effective fees used by Scenarios.
A12: 5. Scenarios: budget → funding goal (grossed up for fees, failed payments, tax reserve and fulfilment) → net proceeds, backers needed, timeline.
A13: 6. Sensitivity and Backer Funnel: how goals and audience needs move with pledge size, cost overruns and conversion.
A15: GOAL FORMULA
... A21: Steam revenue after launch is not modelled; the campaign must fund delivery on its own.

Sheet Inputs
A1: Input | B1: Value | C1: Unit | D1: Source / reasoning
A2: Kickstarter platform fee | B2: 0.05 | C2: % of funds | D2: Verified 2026-10-17: kickstarter.com/help/fees (5% of total funds raised).
A3: Payment processing — percentage (pledges ≥ €10) | B3: 0.03 | C3: % of pledge | D3: Verified 2026-10-17: kickstarter.com/help/fees (Netherlands) — 3% + €0.30 per pledge.
A4: Payment processing — fixed per pledge (≥ €10) | B4: 0.3 | C4: EUR/pledge | D4: Verified 2026-10-17: kickstarter.com/help/fees (Netherlands) — 3% + €0.30 per pledge.
A5: Micropledge processing % (pledges < €10) | B5: 0.05 | C5: % of pledge | D5: Verified 2026-10-17 (Netherlands): 'Pledges under €10 have a discounted micropledge fee of 5% + €0.08'.
A6: Micropledge fixed per pledge (< €10) | B6: 0.08 | C6: EUR/pledge | D6: Verified 2026-10-17 (same page).
A7: Micropledge threshold | B7: 10 | C7: EUR | D7: Verified 2026-10-17 (same page).
A8: FX: USD per 1 EUR | B8: 1.15 | C8: USD/EUR | D8: ASSUMPTION — only converts costs quoted in USD (Steam fee). Check the current rate.
A9: Failed / dropped payments | B9: 0.03 | C9: % of pledged | D9: ASSUMPTION — some pledges fail at card charge; Kickstarter retries for 7 days. No official rate published; 2–5% is a common planning range.
A10: Campaign currency (text, informational) | B10: EUR | D10: Creator resident in the Netherlands (stated 2026-10-17): an individual NL project raises in EUR (help article 16236650).
A11: Tax & compliance reserve | B11: 0.05 | C11: % of pledged | D11: ASSUMPTION — Dutch income tax on the part of the funds that ends up as the creator's own profit, plus filing surprises. Replace with an accountant's figure.
A12: Share of pledges from EU consumers (VAT due inside the pledge) | B12: 0.35 | C12: % of pledged | D12: ASSUMPTION — reward pledges with a direct counter-performance are a VAT-taxable supply under the Dutch view (moore-drv.nl, taxlive.nl; verify with belastingdienst.nl). Kickstarter's automatic VAT handling targets shipped goods, so a Dutch creator of digital rewards is the responsible party. Set to 0 if the Pledge Manager collects VAT on top of pledges.
A13: VAT rate assumed (NL standard rate) | B13: 0.21 | C13: % | D13: 21% NL standard rate. Cross-border EU consumer sales above €10k/yr use the backer's country rate (OSS) — similar range. Small-business scheme (KOR) may exempt below €20k turnover — ask the accountant.
A14: Fulfilment cost per backer (digital) | B14: 0.1 | C14: EUR/backer | D14: ASSUMPTION — Steam keys and Kickstarter Pledge Manager digital delivery cost nothing per key; this covers email-tool overage and support time outside the labor plan.
A15: Entity route: 1 = US company via Stripe Atlas, 0 = an eligible resident launches | B15: 0 | C15: flag | D15: 0: the creator is resident in the Netherlands, an eligible country (stated 2026-10-17). US-company lines then cost nothing.
A16: Stripe Atlas incorporation (one-time) | B16: 500 | C16: USD | D16: Secondary sources (rho.co, unilink.us, 2026): $500 one-time incl. year-1 registered agent. Verify at stripe.com/atlas.
A17: US registered agent renewal (year 2) | B17: 100 | C17: USD/yr | D17: Secondary sources: $100/yr after year 1.
A18: US state annual tax / franchise tax | B18: 300 | C18: USD/yr | D18: Secondary source (unilink.us): ~$300/yr (Delaware). Depends on entity type — verify.
A19: US tax filings by an accountant (foreign-owned company) | B19: 600 | C19: USD/yr | D19: ASSUMPTION — foreign-owned US companies have annual federal information returns; get a quote.
A20: Dutch accountant: income-tax return + VAT returns | B20: 900 | C20: EUR | D20: ASSUMPTION — get a quote; covers the campaign year.
A21: KvK (Chamber of Commerce) registration, if you register as a business | B21: 85 | C21: EUR | D21: ASSUMPTION — one-off KvK fee; check kvk.nl. Likely needed: receiving reward pledges is business activity under the Dutch view.
A22: Steam Direct fee (own App ID) | B22: 100 | C22: USD | D22: Verified 2026-10-17: partner.steamgames.com/doc/gettingstarted/appfee — $100, recoupable after $1,000 revenue.
... A32: Steam beta (Release State Override) key cap for crowdfunding | B32: 2500 | C32: keys | D32: Verified 2026-10-17: partner.steamgames.com/doc/features/keys — 'generally 2,500 total'.

Sheet Labor
A1: Work package (remaining work) | B1: MVD (h) | C1: Realistic (h) | D1: Expanded (h) | E1: What it covers / why (all hours are ASSUMPTIONS — re-estimate with the team)
A2: Fix client-side netId-0 bug + netcode hardening | B2: 80 | C2: 80 | D2: 80 | E2: Critical defect (00 §4): client shark cannot eat. Includes a real Steam 4-PC test matrix.
A3: Bug backlog, stability, crash fixes | B3: 160 | C3: 200 | D3: 240 | E3: From playtest reports; scales with content.
A4: Performance + Low/Medium quality presets (HDRP) | B4: 120 | C4: 140 | D4: 160 | E4: Editor baseline 17.5 ms main / 11–14 ms GPU at 1080p (2026-10-16). Friend groups have mixed PCs.
A5: Onboarding: first-round hints, controls screen | B5: 80 | C5: 100 | D5: 120 | E5: No tutorial exists today.
A6: Controller support complete + key rebinding | B6: 40 | C6: 40 | D6: 60 | E6: Movement has gamepad bindings; UI/tasks unverified.
A7: Steamworks: own App ID, depots, achievements, rich presence | B7: 40 | C7: 50 | D7: 60 | E7: Today the game runs on Valve's test App 480.
A8: Settings & accessibility (push-to-talk, colour-blind glows, captions for alerts) | B8: 60 | C8: 70 | D8: 80 | E8: Voice is core — push-to-talk/open-mic choice is mandatory for comfort.
A9: Balance tuning from playtests | B9: 80 | C9: 120 | D9: 160 | E9: Shark vs fish win-rate targets.
A10: Playtest operations (weekends, surveys, Discord) | B10: 80 | C10: 100 | D10: 120 | E10: Runs from validation through beta.
A11: Backer rewards: credits, Founder cosmetics (2) + selection UI, trawler names | B11: 60 | C11: 60 | D11: 60 | E11: Rewards in 05 that need game work.
A12: Making-of digital book (PDF) | B12: 20 | C12: 20 | D12: 20 | E12: Founder-tier reward; in-engine screenshots + text.
A13: Campaign + store + community management (pre-launch through campaign end) | B13: 200 | C13: 240 | D13: 280 | E13: Clips, posts, updates, comments, outreach.
... A22: Second shark species / role variant — Expanded scope | B22: 0 | C22: 0 | D22: 160 | E22: Needs a licensed model (Costs).
A23: TOTAL remaining hours | B23: =SUM(B2:B22) | C23: =SUM(C2:C22) | D23: =SUM(D2:D22)

Sheet Costs
A1: Cash cost item (non-labor) | B1: Currency | C1: MVD | D1: Realistic | E1: Expanded | F1: MVD (EUR) | G1: Realistic (EUR) | H1: Expanded (EUR) | I1: Source / reasoning
A2: Steam Direct fee | B2: USD | C2: =Inputs!$B$22 | D2: =Inputs!$B$22 | E2: =Inputs!$B$22 | F2: =IF($B2="USD",C2/Inputs!$B$8,C2) | G2: =IF($B2="USD",D2/Inputs!$B$8,D2) | H2: =IF($B2="USD",E2/Inputs!$B$8,E2) | I2: Verified (Inputs).
A3: US company: Stripe Atlas setup | B3: USD | C3: =Inputs!$B$16*Inputs!$B$15 | D3: =Inputs!$B$16*Inputs!$B$15 | E3: =Inputs!$B$16*Inputs!$B$15 | F3: =IF($B3="USD",C3/Inputs!$B$8,C3) | G3: =IF($B3="USD",D3/Inputs!$B$8,D3) | H3: =IF($B3="USD",E3/Inputs!$B$8,E3) | I3: Only if entity route = 1.
A4: US company: year-2 agent + state tax | B4: USD | C4: =(Inputs!$B$17+Inputs!$B$18)*Inputs!$B$15 | D4: =(Inputs!$B$17+Inputs!$B$18)*Inputs!$B$15 | E4: =(Inputs!$B$17+Inputs!$B$18)*Inputs!$B$15 | F4: =IF($B4="USD",C4/Inputs!$B$8,C4) | G4: =IF($B4="USD",D4/Inputs!$B$8,D4) | H4: =IF($B4="USD",E4/Inputs!$B$8,E4) | I4: Delivery runs into a second year.
A5: US company: accountant filings (2 years) | B5: USD | C5: =2*Inputs!$B$19*Inputs!$B$15 | D5: =2*Inputs!$B$19*Inputs!$B$15 | E5: =2*Inputs!$B$19*Inputs!$B$15 | F5: =IF($B5="USD",C5/Inputs!$B$8,C5) | G5: =IF($B5="USD",D5/Inputs!$B$8,D5) | H5: =IF($B5="USD",E5/Inputs!$B$8,E5) | I5: Assumption; get a quote.
A6: Dutch accountant (income tax + VAT) | B6: EUR | C6: =Inputs!$B$20 | D6: =Inputs!$B$20*1.5 | E6: =Inputs!$B$20*2 | F6: =IF($B6="USD",C6/Inputs!$B$8,C6) | G6: =IF($B6="USD",D6/Inputs!$B$8,D6) | H6: =IF($B6="USD",E6/Inputs!$B$8,E6) | I6: Assumption: longer delivery = more filing years.
A7: KvK registration | B7: EUR | C7: =Inputs!$B$21 | D7: =Inputs!$B$21 | E7: =Inputs!$B$21 | F7: =IF($B7="USD",C7/Inputs!$B$8,C7) | G7: =IF($B7="USD",D7/Inputs!$B$8,D7) | H7: =IF($B7="USD",E7/Inputs!$B$8,E7) | I7: Assumption.
A8: Original music (score + jingles) | B8: EUR | C8: 0 | D8: 2500 | E8: 5000 | F8: =IF($B8="USD",C8/Inputs!$B$8,C8) | G8: =IF($B8="USD",D8/Inputs!$B$8,D8) | H8: =IF($B8="USD",E8/Inputs!$B$8,E8) | I8: Current music is CC0 third-party and fine to ship; an original score lets the team offer a soundtrack later. Freelance quote needed.
A9: Sound design pack licences | B9: EUR | C9: 0 | D9: 500 | E9: 1500 | F9: =IF($B9="USD",C9/Inputs!$B$8,C9) | G9: =IF($B9="USD",D9/Inputs!$B$8,D9) | H9: =IF($B9="USD",E9/Inputs!$B$8,E9) | I9: Asset-store / library SFX; assumption.
A10: Art: environment packs for second/third map | B10: EUR | C10: 0 | D10: 400 | E10: 900 | F10: =IF($B10="USD",C10/Inputs!$B$8,C10) | G10: =IF($B10="USD",D10/Inputs!$B$8,D10) | H10: =IF($B10="USD",E10/Inputs!$B$8,E10) | I10: Asset-store packs; check licences allow marketing renders.
A11: Art: licensed model for second shark species | B11: EUR | C11: 0 | D11: 0 | E11: 1500 | F11: =IF($B11="USD",C11/Inputs!$B$8,C11) | G11: =IF($B11="USD",D11/Inputs!$B$8,D11) | H11: =IF($B11="USD",E11/Inputs!$B$8,E11) | I11: Expanded only; freelance or store model.
A12: Freelance artist contract (Expanded) | B12: EUR | C12: 0 | D12: 0 | E12: 6000 | F12: =IF($B12="USD",C12/Inputs!$B$8,C12) | G12: =IF($B12="USD",D12/Inputs!$B$8,D12) | H12: =IF($B12="USD",E12/Inputs!$B$8,E12) | I12: Expanded only: ~3 months part-time 3D/tech-art help. Assumption.
A13: Localization: translation (6 languages Realistic / 10 Expanded) | B13: EUR | C13: 0 | D13: 2400 | E13: 4000 | F13: =IF($B13="USD",C13/Inputs!$B$8,C13) | G13: =IF($B13="USD",D13/Inputs!$B$8,D13) | H13: =IF($B13="USD",E13/Inputs!$B$8,E13) | I13: ≈4,000 words × €0.10/word × languages (assumption; get quotes). MVD ships English only.
A14: Compatibility hardware (used low-end GPU / Steam Deck) | B14: EUR | C14: 300 | D14: 900 | E14: 1200 | F14: =IF($B14="USD",C14/Inputs!$B$8,C14) | G14: =IF($B14="USD",D14/Inputs!$B$8,D14) | H14: =IF($B14="USD",E14/Inputs!$B$8,E14) | I14: Assumption. Steam Deck only from Realistic.
A15: Software, domain, email tool, misc. services | B15: EUR | C15: 60 | D15: 150 | E15: 300 | F15: =IF($B15="USD",C15/Inputs!$B$8,C15) | G15: =IF($B15="USD",D15/Inputs!$B$8,D15) | H15: =IF($B15="USD",E15/Inputs!$B$8,E15) | I15: Unity Personal is free below its revenue/funding threshold (verify current threshold at unity.com before launch). Steam relay + voice cost nothing.
A16: Pre-launch ads: Kickstarter-follower & email lead ads | B16: EUR | C16: 750 | D16: 1000 | E16: 1500 | F16: =IF($B16="USD",C16/Inputs!$B$8,C16) | G16: =IF($B16="USD",D16/Inputs!$B$8,D16) | H16: =IF($B16="USD",E16/Inputs!$B$8,E16) | I16: Full Charge playbook: start $5–10/day, test 3–4 creatives; benchmark $1.70–2.50 per KS follower with strong gameplay creative → ~300–440 followers at MVD spend. Only with explicit approval.
A17: Live-campaign ads (Meta/Reddit), retargeting | B17: EUR | C17: 1500 | D17: 3000 | E17: 6000 | F17: =IF($B17="USD",C17/Inputs!$B$8,C17) | G17: =IF($B17="USD",D17/Inputs!$B$8,D17) | H17: =IF($B17="USD",E17/Inputs!$B$8,E17) | I17: Guide: 20–30% of goal to ads when starting from scratch; Boo Croo budgeted 10% marketing. Pause if ad cost per backer > net per backer (dashboard T6).
A18: Campaign video: music licence / voice-over / stock SFX | B18: EUR | C18: 0 | D18: 300 | E18: 600 | F18: =IF($B18="USD",C18/Inputs!$B$8,C18) | G18: =IF($B18="USD",D18/Inputs!$B$8,D18) | H18: =IF($B18="USD",E18/Inputs!$B$8,E18) | I18: MVD uses CC0 music + founders' own voice-over.
A19: Press/creator kit hosting, keys service | B19: EUR | C19: 0 | D19: 0 | E19: 0 | F19: =IF($B19="USD",C19/Inputs!$B$8,C19) | G19: =IF($B19="USD",D19/Inputs!$B$8,D19) | H19: =IF($B19="USD",E19/Inputs!$B$8,E19) | I19: Free tools (Steam keys, presskit pages).
A20: TOTAL cash costs (EUR) | F20: =SUM(F2:F19) | G20: =SUM(G2:G19) | H20: =SUM(H2:H19)

Sheet Rewards
A1: Tier | B1: Price (EUR) | C1: Limit | D1: Mix (share of backers) | E1: Steam keys incl. | F1: Fulfilment €/backer | G1: Proc. % | H1: Fixed fee € | I1: Total fee €/pledge | J1: Net €/backer | K1: € share (weight) | L1: Includes | M1: Target segment | N1: Delivery | O1: Complexity | P1: Main risk
A2: Ripple (thank you) | B2: 5 | C2: — | D2: 0.07 | E2: 0 | F2: 0 | G2: =IF(B2<Inputs!$B$7,Inputs!$B$5,Inputs!$B$3) | H2: =IF(B2<Inputs!$B$7,Inputs!$B$6,Inputs!$B$4) | I2: =B2*(Inputs!$B$2+G2+Inputs!$B$9+Inputs!$B$11+Inputs!$B$12*Inputs!$B$13/(1+Inputs!$B$13))+H2 | J2: =B2-I2-F2-Inputs!$B$14 | K2: =B2*D2 | L2: Name in in-game Supporters credits; backer Discord role; 4K wallpaper pack (from master key art). | M2: Friends & well-wishers | N2: Jun 2027 | O2: Very low | P2: None material.
A3: Early Diver (limited) | B3: 12 | C3: 300 | D3: 0.18 | E3: 1 | F3: 0 | G3: =IF(B3<Inputs!$B$7,Inputs!$B$5,Inputs!$B$3) | H3: =IF(B3<Inputs!$B$7,Inputs!$B$6,Inputs!$B$4) | I3: =B3*(Inputs!$B$2+G3+Inputs!$B$9+Inputs!$B$11+Inputs!$B$12*Inputs!$B$13/(1+Inputs!$B$13))+H3 | J3: =B3-I3-F3-Inputs!$B$14 | K3: =B3*D3 | L3: 1 Steam key for Reef Run (backer beta, then full game); name in Supporters credits. | M3: Early S1/S3 backers | N3: Beta: Jul 2027 | O3: Low | P3: Below the planned €12.99 retail → plan a Steam launch discount for parity (Steam key rules).
A4: Diver | B4: 15 | C4: — | D4: 0.2 | E4: 1 | F4: 0 | G4: =IF(B4<Inputs!$B$7,Inputs!$B$5,Inputs!$B$3) | H4: =IF(B4<Inputs!$B$7,Inputs!$B$6,Inputs!$B$4) | I4: =B4*(Inputs!$B$2+G4+Inputs!$B$9+Inputs!$B$11+Inputs!$B$12*Inputs!$B$13/(1+Inputs!$B$13))+H4 | J4: =B4-I4-F4-Inputs!$B$14 | K4: =B4*D4 | L4: Same as Early Diver. | M4: S1/S3 | N4: Beta: Jul 2027 | O4: Low | P4: Beta-key cap 2,500 (Steam).
A5: Founding Diver | B5: 29 | C5: — | D5: 0.22 | E5: 1 | F5: 0 | G5: =IF(B5<Inputs!$B$7,Inputs!$B$5,Inputs!$B$3) | H5: =IF(B5<Inputs!$B$7,Inputs!$B$6,Inputs!$B$4) | I5: =B5*(Inputs!$B$2+G5+Inputs!$B$9+Inputs!$B$11+Inputs!$B$12*Inputs!$B$13/(1+Inputs!$B$13))+H5 | J5: =B5-I5-F5-Inputs!$B$14 | K5: =B5*D5 | L5: Diver + Founder cosmetics (fish 'Founder Fin' pattern + shark 'Old Scar' skin) + Founders credits section + Making-of PDF. | M5: S3, S2 | N5: Key Jul 2027 · cosmetics at 1.0 | O5: Medium | P5: Cosmetics need a selection UI + network sync (in Labor).
A6: Pod of Four | B6: 49 | C6: — | D6: 0.2 | E6: 4 | F6: 0 | G6: =IF(B6<Inputs!$B$7,Inputs!$B$5,Inputs!$B$3) | H6: =IF(B6<Inputs!$B$7,Inputs!$B$6,Inputs!$B$4) | I6: =B6*(Inputs!$B$2+G6+Inputs!$B$9+Inputs!$B$11+Inputs!$B$12*Inputs!$B$13/(1+Inputs!$B$13))+H6 | J6: =B6-I6-F6-Inputs!$B$14 | K6: =B6*D6 | L6: 4 Steam keys (for your group) + beta access for all 4 + 4 names in Supporters credits. | M6: S1 friend groups | N6: Beta: Jul 2027 | O6: Low | P6: Uses 4 beta keys each → watch the 2,500 cap.
A7: Founding Pod | B7: 99 | C7: — | D7: 0.1 | E7: 4 | F7: 0 | G7: =IF(B7<Inputs!$B$7,Inputs!$B$5,Inputs!$B$3) | H7: =IF(B7<Inputs!$B$7,Inputs!$B$6,Inputs!$B$4) | I7: =B7*(Inputs!$B$2+G7+Inputs!$B$9+Inputs!$B$11+Inputs!$B$12*Inputs!$B$13/(1+Inputs!$B$13))+H7 | J7: =B7-I7-F7-Inputs!$B$14 | K7: =B7*D7 | L7: Pod of Four + Founder cosmetics ×4 + 4 Founders credits + Making-of PDF. | M7: Committed groups, S3 | N7: Keys Jul 2027 · cosmetics at 1.0 | O7: Medium | P7: Same as Founding Diver.
A8: Name the Trawler (limited) | B8: 199 | C8: 25 | D8: 0.03 | E8: 1 | F8: 2 | G8: =IF(B8<Inputs!$B$7,Inputs!$B$5,Inputs!$B$3) | H8: =IF(B8<Inputs!$B$7,Inputs!$B$6,Inputs!$B$4) | I8: =B8*(Inputs!$B$2+G8+Inputs!$B$9+Inputs!$B$11+Inputs!$B$12*Inputs!$B$13/(1+Inputs!$B$13))+H8 | J8: =B8-I8-F8-Inputs!$B$14 | K8: =B8*D8 | L8: Founding Diver + your name (moderated) painted on the trawler that sweeps the reef — one name shown per round, rotating. | M8: Superfans | N8: At 1.0 | O8: Medium | P8: Moderation of names; ~0.5 h each (in Labor).
A10: Mix check (must be 100%) | D10: =SUM(D2:D8)
A11: Blended average pledge (EUR) | B11: =SUMPRODUCT(B2:B8,D2:D8)/SUM(D2:D8)
A12: Effective processing % (dollar-weighted) | B12: =SUMPRODUCT(G2:G8,K2:K8)/SUM(K2:K8)
A13: Effective fixed fee per pledge (EUR) | B13: =SUMPRODUCT(H2:H8,D2:D8)/SUM(D2:D8)
A14: Tier fulfilment per backer, blended (EUR) | B14: =SUMPRODUCT(F2:F8,D2:D8)/SUM(D2:D8)
A15: Steam keys per backer, blended | B15: =SUMPRODUCT(E2:E8,D2:D8)/SUM(D2:D8)
A17: Mix shares are ASSUMPTIONS informed by comparable campaigns (01 §3.3: cheapest game tier and friend packs draw most backers). Replace with real data after launch day 3.

Sheet Scenarios
A1: Line | B1: MVD | C1: Realistic | D1: Expanded | E1: Notes
A2: Scope (what backers are promised) | B2: Current game, finished & polished | C2: + 2nd map, 2 tasks, 6 languages, score, Deck | D2: + 3rd map, AI fill-ins, 2nd shark | E2: Only the funded scenario's scope may be promised (05).
A3: Remaining labor (hours) | B3: =Labor!B23 | C3: =Labor!C23 | D3: =Labor!D23
A4: Stipend paid to team (EUR per hour, fully loaded) | B4: 10 | C4: 12 | D4: 15 | E4: ASSUMPTION — a modest stipend so members can commit hours; includes employer/freelancer social charges. Team must confirm.
A5: Share of hours paid from the campaign | B5: 0.5 | C5: 1 | D5: 1 | E5: MVD pays half the hours; the rest is unpaid founder time (disclosed below).
A6: Team stipends (EUR) | B6: =B3*B4*B5 | C6: =C3*C4*C5 | D6: =D3*D4*D5
A7: Non-labor cash costs (EUR) | B7: =Costs!F20 | C7: =Costs!G20 | D7: =Costs!H20
A8: Subtotal | B8: =B6+B7 | C8: =C6+C7 | D8: =D6+D7
A9: Contingency | B9: =B8*Inputs!$B$23 | C9: =C8*Inputs!$B$23 | D9: =D8*Inputs!$B$23
A10: TOTAL DEVELOPMENT BUDGET (cash the team must receive) | B10: =B8+B9 | C10: =C8+C9 | D10: =D8+D9
A11: Average pledge used (EUR) | B11: =Rewards!$B$11 | C11: =Rewards!$B$11 | D11: =Rewards!$B$11 | E11: From Rewards (blended mix).
A12: Deductions as % of pledged (fee + proc. + drops + tax + VAT + per-pledge costs) | B12: =Inputs!$B$2+Rewards!$B$12+Inputs!$B$9+Inputs!$B$11+Inputs!$B$12*Inputs!$B$13/(1+Inputs!$B$13)+(Rewards!$B$13+Inputs!$B$14+Rewards!$B$14)/B11 | C12: =Inputs!$B$2+Rewards!$B$12+Inputs!$B$9+Inputs!$B$11+Inputs!$B$12*Inputs!$B$13/(1+Inputs!$B$13)+(Rewards!$B$13+Inputs!$B$14+Rewards!$B$14)/C11 | D12: =Inputs!$B$2+Rewards!$B$12+Inputs!$B$9+Inputs!$B$11+Inputs!$B$12*Inputs!$B$13/(1+Inputs!$B$13)+(Rewards!$B$13+Inputs!$B$14+Rewards!$B$14)/D11
A13: Goal before rounding | B13: =B10/(1-B12) | C13: =C10/(1-C12) | D13: =D10/(1-D12)
A14: FUNDING GOAL (rounded up to €500) | B14: =ROUNDUP(B13/500,0)*500 | C14: =ROUNDUP(C13/500,0)*500 | D14: =ROUNDUP(D13/500,0)*500 | E14: Kickstarter test: at exactly 100% can we deliver? Yes by construction.
A15: Backers needed at average pledge | B15: =ROUNDUP(B14/B11,0) | C15: =ROUNDUP(C14/C11,0) | D15: =ROUNDUP(D14/D11,0)
A16: Kickstarter fee at goal | B16: =B14*Inputs!$B$2 | C16: =C14*Inputs!$B$2 | D16: =D14*Inputs!$B$2
A17: Payment processing at goal | B17: =B14*Rewards!$B$12+B15*Rewards!$B$13 | C17: =C14*Rewards!$B$12+C15*Rewards!$B$13 | D17: =D14*Rewards!$B$12+D15*Rewards!$B$13
A18: Failed payments at goal | B18: =B14*Inputs!$B$9 | C18: =C14*Inputs!$B$9 | D18: =D14*Inputs!$B$9
A19: Tax & compliance reserve | B19: =B14*Inputs!$B$11 | C19: =C14*Inputs!$B$11 | D19: =D14*Inputs!$B$11
A20: VAT inside pledges (EU consumers) | B20: =B14*Inputs!$B$12*Inputs!$B$13/(1+Inputs!$B$13) | C20: =C14*Inputs!$B$12*Inputs!$B$13/(1+Inputs!$B$13) | D20: =D14*Inputs!$B$12*Inputs!$B$13/(1+Inputs!$B$13)
A21: Reward fulfilment | B21: =B15*(Inputs!$B$14+Rewards!$B$14) | C21: =C15*(Inputs!$B$14+Rewards!$B$14) | D21: =D15*(Inputs!$B$14+Rewards!$B$14)
A22: NET PROCEEDS at exactly 100% funded | B22: =B14-B16-B17-B18-B19-B20-B21 | C22: =C14-C16-C17-C18-C19-C20-C21 | D22: =D14-D16-D17-D18-D19-D20-D21
A23: Net minus budget (must be ≥ 0) | B23: =B22-B10 | C23: =C22-C10 | D23: =D22-D10
A24: Backers needed if average pledge = €15 | B24: =ROUNDUP(B14/15,0) | C24: =ROUNDUP(C14/15,0) | D24: =ROUNDUP(D14/15,0)
A25: Backers needed if average pledge = €22 | B25: =ROUNDUP(B14/22,0) | C25: =ROUNDUP(C14/22,0) | D25: =ROUNDUP(D14/22,0)
A26: Backers needed if average pledge = €30 | B26: =ROUNDUP(B14/30,0) | C26: =ROUNDUP(C14/30,0) | D26: =ROUNDUP(D14/30,0)
A27: Backers needed if average pledge = €40 | B27: =ROUNDUP(B14/40,0) | C27: =ROUNDUP(C14/40,0) | D27: =ROUNDUP(D14/40,0)
A28: Steam keys owed at goal (all tiers) | B28: =ROUNDUP(B15*Rewards!$B$15,0) | C28: =ROUNDUP(C15*Rewards!$B$15,0) | D28: =ROUNDUP(D15*Rewards!$B$15,0) | E28: Beta access beyond the cap is served with Steam Playtest keys (free, never sold).
A29: Keys within Steam's 2,500 beta-key cap? | B29: =IF(B28<=Inputs!$B$32,"Yes","No — use Playtest keys for the rest") | C29: =IF(C28<=Inputs!$B$32,"Yes","No — use Playtest keys for the rest") | D29: =IF(D28<=Inputs!$B$32,"Yes","No — use Playtest keys for the rest")
A30: Development time at team capacity (months) | B30: =B3/Inputs!$B$24/4.345 | C30: =C3/Inputs!$B$24/4.345 | D30: =D3/Inputs!$B$24/4.345 | E30: Hours ÷ weekly capacity. Add campaign + payout lag (~2 months) for calendar dates.
A31: Promised full-release window (calendar, with buffer) | B31: Q4 2027 | C31: Q1 2028 (2nd map Q2 2028) | D31: Q4 2028 | E31: Campaign assumed Apr–May 2027 (after Next Fest Feb 2027). Buffer ≥ 30% on top of the hours estimate.
A32: Unpaid founder labor value (NOT cash, NOT in goal) | B32: =B3*Inputs!$B$25-B6 | C32: =C3*Inputs!$B$25-C6 | D32: =D3*Inputs!$B$25-D6 | E32: Disclosed so nobody mistakes the goal for the game's real cost.
A33: Major financial risks | B33: Team availability; any cost overrun eats unpaid time | C33: Hours under-estimated for map 2; translation quality | D33: Scope creep; AI fill-ins are technically risky

Sheet Sensitivity
A1: 1. Backers needed by goal and average pledge
A2: Average pledge → | B2: 15 | C2: 20 | D2: 25 | E2: 30 | F2: 35 | G2: 40
A3: ="MVD goal "&TEXT(Scenarios!B14,"€#,##0") | B3: =ROUNDUP(Scenarios!$B$14/B$2,0) | C3: =ROUNDUP(Scenarios!$B$14/C$2,0) | D3: =ROUNDUP(Scenarios!$B$14/D$2,0) | E3: =ROUNDUP(Scenarios!$B$14/E$2,0) | F3: =ROUNDUP(Scenarios!$B$14/F$2,0) | G3: =ROUNDUP(Scenarios!$B$14/G$2,0)
A4: ="Realistic goal "&TEXT(Scenarios!C14,"€#,##0") | B4: =ROUNDUP(Scenarios!$C$14/B$2,0) | C4: =ROUNDUP(Scenarios!$C$14/C$2,0) | D4: =ROUNDUP(Scenarios!$C$14/D$2,0) | E4: =ROUNDUP(Scenarios!$C$14/E$2,0) | F4: =ROUNDUP(Scenarios!$C$14/F$2,0) | G4: =ROUNDUP(Scenarios!$C$14/G$2,0)
A5: ="Expanded goal "&TEXT(Scenarios!D14,"€#,##0") | B5: =ROUNDUP(Scenarios!$D$14/B$2,0) | C5: =ROUNDUP(Scenarios!$D$14/C$2,0) | D5: =ROUNDUP(Scenarios!$D$14/D$2,0) | E5: =ROUNDUP(Scenarios!$D$14/E$2,0) | F5: =ROUNDUP(Scenarios!$D$14/F$2,0) | G5: =ROUNDUP(Scenarios!$D$14/G$2,0)
A8: 2. Cost overrun: Realistic budget if hours run over and stipend changes
A9: Stipend €/h ↓ · hours multiplier → | B9: 0.8 | C9: 1 | D9: 1.25 | E9: 1.5
A10: 8 | B10: =(Scenarios!$C$3*B$9*$A10*Scenarios!$C$5+Scenarios!$C$7)*(1+Inputs!$B$23) | C10: =(Scenarios!$C$3*C$9*$A10*Scenarios!$C$5+Scenarios!$C$7)*(1+Inputs!$B$23) | D10: =(Scenarios!$C$3*D$9*$A10*Scenarios!$C$5+Scenarios!$C$7)*(1+Inputs!$B$23) | E10: =(Scenarios!$C$3*E$9*$A10*Scenarios!$C$5+Scenarios!$C$7)*(1+Inputs!$B$23)
A11: 10 | B11: =(Scenarios!$C$3*B$9*$A11*Scenarios!$C$5+Scenarios!$C$7)*(1+Inputs!$B$23) | C11: =(Scenarios!$C$3*C$9*$A11*Scenarios!$C$5+Scenarios!$C$7)*(1+Inputs!$B$23) | D11: =(Scenarios!$C$3*D$9*$A11*Scenarios!$C$5+Scenarios!$C$7)*(1+Inputs!$B$23) | E11: =(Scenarios!$C$3*E$9*$A11*Scenarios!$C$5+Scenarios!$C$7)*(1+Inputs!$B$23)
A12: 12 | B12: =(Scenarios!$C$3*B$9*$A12*Scenarios!$C$5+Scenarios!$C$7)*(1+Inputs!$B$23) | C12: =(Scenarios!$C$3*C$9*$A12*Scenarios!$C$5+Scenarios!$C$7)*(1+Inputs!$B$23) | D12: =(Scenarios!$C$3*D$9*$A12*Scenarios!$C$5+Scenarios!$C$7)*(1+Inputs!$B$23) | E12: =(Scenarios!$C$3*E$9*$A12*Scenarios!$C$5+Scenarios!$C$7)*(1+Inputs!$B$23)
A13: 15 | B13: =(Scenarios!$C$3*B$9*$A13*Scenarios!$C$5+Scenarios!$C$7)*(1+Inputs!$B$23) | C13: =(Scenarios!$C$3*C$9*$A13*Scenarios!$C$5+Scenarios!$C$7)*(1+Inputs!$B$23) | D13: =(Scenarios!$C$3*D$9*$A13*Scenarios!$C$5+Scenarios!$C$7)*(1+Inputs!$B$23) | E13: =(Scenarios!$C$3*E$9*$A13*Scenarios!$C$5+Scenarios!$C$7)*(1+Inputs!$B$23)
A14: 20 | B14: =(Scenarios!$C$3*B$9*$A14*Scenarios!$C$5+Scenarios!$C$7)*(1+Inputs!$B$23) | C14: =(Scenarios!$C$3*C$9*$A14*Scenarios!$C$5+Scenarios!$C$7)*(1+Inputs!$B$23) | D14: =(Scenarios!$C$3*D$9*$A14*Scenarios!$C$5+Scenarios!$C$7)*(1+Inputs!$B$23) | E14: =(Scenarios!$C$3*E$9*$A14*Scenarios!$C$5+Scenarios!$C$7)*(1+Inputs!$B$23)
A15: Compare with the Realistic goal's net proceeds → | B15: =Scenarios!C22
A17: 3. What the team receives if the MVD campaign over-funds
A18: Funded % → | B18: 1 | C18: 1.25 | D18: 1.5 | E18: 2 | F18: 3
A19: Pledged (EUR) | B19: =Scenarios!$B$14*B18 | C19: =Scenarios!$B$14*C18 | D19: =Scenarios!$B$14*D18 | E19: =Scenarios!$B$14*E18 | F19: =Scenarios!$B$14*F18
A20: Net proceeds (EUR) | B20: =B19*(1-Scenarios!$B$12) | C20: =C19*(1-Scenarios!$B$12) | D20: =D19*(1-Scenarios!$B$12) | E20: =E19*(1-Scenarios!$B$12) | F20: =F19*(1-Scenarios!$B$12)
A21: Surplus over MVD budget (EUR) | B21: =B20-Scenarios!$B$10 | C21: =C20-Scenarios!$B$10 | D21: =D20-Scenarios!$B$10 | E21: =E20-Scenarios!$B$10 | F21: =F20-Scenarios!$B$10
A22: Covers Realistic budget? | B22: =IF(B20>=Scenarios!$C$10,"Yes","No") | C22: =IF(C20>=Scenarios!$C$10,"Yes","No") | D22: =IF(D20>=Scenarios!$C$10,"Yes","No") | E22: =IF(E20>=Scenarios!$C$10,"Yes","No") | F22: =IF(F20>=Scenarios!$C$10,"Yes","No")
A24: 4. Fee drag by average pledge (fixed fee matters for small pledges)
A25: Average pledge → | B25: 15 | C25: 20 | D25: 25 | E25: 30 | F25: 35 | G25: 40
A26: Kickstarter + processing as % of pledge | B26: =Inputs!$B$2+IF(B25<Inputs!$B$7,Inputs!$B$5+Inputs!$B$6/B25,Inputs!$B$3+Inputs!$B$4/B25) | C26: =Inputs!$B$2+IF(C25<Inputs!$B$7,Inputs!$B$5+Inputs!$B$6/C25,Inputs!$B$3+Inputs!$B$4/C25) | D26: =Inputs!$B$2+IF(D25<Inputs!$B$7,Inputs!$B$5+Inputs!$B$6/D25,Inputs!$B$3+Inputs!$B$4/D25) | E26: =Inputs!$B$2+IF(E25<Inputs!$B$7,Inputs!$B$5+Inputs!$B$6/E25,Inputs!$B$3+Inputs!$B$4/E25) | F26: =Inputs!$B$2+IF(F25<Inputs!$B$7,Inputs!$B$5+Inputs!$B$6/F25,Inputs!$B$3+Inputs!$B$4/F25) | G26: =Inputs!$B$2+IF(G25<Inputs!$B$7,Inputs!$B$5+Inputs!$B$6/G25,Inputs!$B$3+Inputs!$B$4/G25)

Sheet Backer Funnel
A1: Audience needed before launch | B1: MVD | C1: Realistic | D1: Expanded | E1: Notes
A2: Funding goal | B2: =Scenarios!B14 | C2: =Scenarios!C14 | D2: =Scenarios!D14
A3: Backers needed (blended average pledge) | B3: =Scenarios!B15 | C3: =Scenarios!C15 | D3: =Scenarios!D15
A4: Backers expected from followers + email | B4: =ROUNDUP(B3*Inputs!$B$26,0) | C4: =ROUNDUP(C3*Inputs!$B$26,0) | D4: =ROUNDUP(D3*Inputs!$B$26,0) | E4: Inputs: share from followers.
A5: KS pre-launch followers needed — LOW conversion | B5: =ROUNDUP(B4/Inputs!$B$27,0) | C5: =ROUNDUP(C4/Inputs!$B$27,0) | D5: =ROUNDUP(D4/Inputs!$B$27,0) | E5: If conversion is 10%.
A6: KS pre-launch followers needed — MID conversion | B6: =ROUNDUP(B4/Inputs!$B$28,0) | C6: =ROUNDUP(C4/Inputs!$B$28,0) | D6: =ROUNDUP(D4/Inputs!$B$28,0) | E6: If conversion is 20%.
A7: KS pre-launch followers needed — HIGH conversion | B7: =ROUNDUP(B4/Inputs!$B$29,0) | C7: =ROUNDUP(C4/Inputs!$B$29,0) | D7: =ROUNDUP(D4/Inputs!$B$29,0) | E7: If conversion is 30%.
A8: …or email subscribers needed (email conversion) | B8: =ROUNDUP(B4/Inputs!$B$30,0) | C8: =ROUNDUP(C4/Inputs!$B$30,0) | D8: =ROUNDUP(D4/Inputs!$B$30,0) | E8: If the list alone had to deliver it.
A9: Steam wishlists implied (proxy only) | B9: =ROUNDUP(B3/Inputs!$B$31,0) | C9: =ROUNDUP(C3/Inputs!$B$31,0) | D9: =ROUNDUP(D3/Inputs!$B$31,0) | E9: Wishlists needed if ALL backers came from wishlisters at the assumed rate — shows why wishlists alone are not enough.
A10: Pledges/day needed (30-day campaign, flat) | B10: =B3/30 | C10: =C3/30 | D10: =D3/30 | E10: Real campaigns front-load: ~30–40% of total in the first 72 h is typical (assumption).
