Workbook

Sheet README
A1: REEF RUN — Kickstarter campaign dashboard (11_CAMPAIGN_DASHBOARD.md)
A2: Inputs: copy the goal and planned average pledge from 03_funding_model.xlsx (Scenarios), set the launch date. No cross-file links, on purpose.
A3: Pre-launch: one row per day for the 6 weeks before launch (Kickstarter followers from the pre-launch page, email list, wishlists).
A4: Daily: fill one row per campaign day from the Kickstarter creator dashboard (pledged, backers, cancellations, visits by referrer) and your ad accounts.
A5: Forecast: three cumulative-share curves (yellow, assumptions). Forecast = pledged so far ÷ share of the total a campaign usually has by that day.
A6: Triggers: each row turns red when its condition is met. The response for each is in 11_CAMPAIGN_DASHBOARD.md §4.
A7: Grey italic first row in each log = EXAMPLE. Overwrite it with day 1.

Sheet Inputs
A1: Funding goal (EUR) | B1: 14000 | C1: From 03_funding_model.xlsx → Scenarios, FUNDING GOAL (MVD)
A2: Planned average pledge (EUR) | B2: 37.56 | C2: From 03 → Rewards (blended)
A3: Launch date | B3: 46490 | C3: Provisional (03 §5). Type a real date.
A4: Campaign length (days) | B4: 30 | C4: Max 30 because of Steam key rules (S3)
A5: Marketing budget for the campaign (EUR) | B5: 1500 | C5: 03 Costs, MVD (live-campaign ads; v2)
A6: Net revenue per backer used to judge ads (EUR) | B6: 28.8 | C6: ≈ average pledge × (1 − 23.3% deductions incl. VAT), from 03 v2
A7: Kickstarter followers at launch (type on launch day) | B7: 0 | C7: From the pre-launch page
A8: Cancellation alert threshold (% of pledged) | B8: 0.05 | C8: Assumption

Sheet Pre-launch
A1: Days to launch | B1: Date | C1: KS followers (total) | D1: Email subscribers (total) | E1: Steam wishlists (total) | F1: Expected launch backers (followers×20% + email×4%) | G1: Share of goal covered at launch | H1: Notes
A2: 42 | B2: =Inputs!$B$3-A2 | C2: 310 | D2: 900 | E2: 5200 | F2: =IF(C2="","",C2*0.2+D2*0.04) | G2: =IF(F2="","",F2*Inputs!$B$2/Inputs!$B$1) | H2: EXAMPLE ROW
A3: 41 | B3: =Inputs!$B$3-A3 | F3: =IF(C3="","",C3*0.2+D3*0.04) | G3: =IF(F3="","",F3*Inputs!$B$2/Inputs!$B$1)
A4: 40 | B4: =Inputs!$B$3-A4 | F4: =IF(C4="","",C4*0.2+D4*0.04) | G4: =IF(F4="","",F4*Inputs!$B$2/Inputs!$B$1)
A5: 39 | B5: =Inputs!$B$3-A5 | F5: =IF(C5="","",C5*0.2+D5*0.04) | G5: =IF(F5="","",F5*Inputs!$B$2/Inputs!$B$1)
A6: 38 | B6: =Inputs!$B$3-A6 | F6: =IF(C6="","",C6*0.2+D6*0.04) | G6: =IF(F6="","",F6*Inputs!$B$2/Inputs!$B$1)
A7: 37 | B7: =Inputs!$B$3-A7 | F7: =IF(C7="","",C7*0.2+D7*0.04) | G7: =IF(F7="","",F7*Inputs!$B$2/Inputs!$B$1)
A8: 36 | B8: =Inputs!$B$3-A8 | F8: =IF(C8="","",C8*0.2+D8*0.04) | G8: =IF(F8="","",F8*Inputs!$B$2/Inputs!$B$1)
A9: 35 | B9: =Inputs!$B$3-A9 | F9: =IF(C9="","",C9*0.2+D9*0.04) | G9: =IF(F9="","",F9*Inputs!$B$2/Inputs!$B$1)
A10: 34 | B10: =Inputs!$B$3-A10 | F10: =IF(C10="","",C10*0.2+D10*0.04) | G10: =IF(F10="","",F10*Inputs!$B$2/Inputs!$B$1)
A11: 33 | B11: =Inputs!$B$3-A11 | F11: =IF(C11="","",C11*0.2+D11*0.04) | G11: =IF(F11="","",F11*Inputs!$B$2/Inputs!$B$1)
A12: 32 | B12: =Inputs!$B$3-A12 | F12: =IF(C12="","",C12*0.2+D12*0.04) | G12: =IF(F12="","",F12*Inputs!$B$2/Inputs!$B$1)
A13: 31 | B13: =Inputs!$B$3-A13 | F13: =IF(C13="","",C13*0.2+D13*0.04) | G13: =IF(F13="","",F13*Inputs!$B$2/Inputs!$B$1)
A14: 30 | B14: =Inputs!$B$3-A14 | F14: =IF(C14="","",C14*0.2+D14*0.04) | G14: =IF(F14="","",F14*Inputs!$B$2/Inputs!$B$1)
... A43: 1 | B43: =Inputs!$B$3-A43 | F43: =IF(C43="","",C43*0.2+D43*0.04) | G43: =IF(F43="","",F43*Inputs!$B$2/Inputs!$B$1)

Sheet Daily
A1: Day | B1: Date | C1: Pledged today (EUR) | D1: New backers today | E1: Cancelled today (EUR) | F1: Cancelled backers today | G1: Net pledged (cumulative) | H1: Backers (cumulative) | I1: Funded % | J1: Average pledge | K1: Visits today | L1: Conversion (new backers ÷ visits) | M1: Visits: Kickstarter | N1: Visits: email | O1: Visits: social | P1: Visits: creators/press | Q1: Visits: ads | R1: Ad spend today (EUR) | S1: Ad-attributed backers | T1: Ad cost per backer | U1: Days left | V1: Needed per remaining day (EUR) | W1: Notes / what we did
A2: 1 | B2: =Inputs!$B$3+A2-1 | C2: 2900 | D2: 101 | E2: 0 | F2: 0 | G2: =IF(C2="","",SUM($C$2:C2)-SUM($E$2:E2)) | H2: =IF(D2="","",SUM($D$2:D2)-SUM($F$2:F2)) | I2: =IF(G2="","",G2/Inputs!$B$1) | J2: =IF(OR(H2="",H2=0),"",G2/H2) | K2: 1650 | L2: =IF(OR(K2="",K2=0),"",D2/K2) | M2: 700 | N2: 380 | O2: 320 | P2: 150 | Q2: 100 | R2: 60 | S2: 2 | T2: =IF(OR(S2="",S2=0),"",R2/S2) | U2: =Inputs!$B$4-A2 | V2: =IF(OR(G2="",U2<=0),"",MAX(0,Inputs!$B$1-G2)/U2) | W2: EXAMPLE ROW — replace with real day 1
A3: 2 | B3: =Inputs!$B$3+A3-1 | G3: =IF(C3="","",SUM($C$2:C3)-SUM($E$2:E3)) | H3: =IF(D3="","",SUM($D$2:D3)-SUM($F$2:F3)) | I3: =IF(G3="","",G3/Inputs!$B$1) | J3: =IF(OR(H3="",H3=0),"",G3/H3) | L3: =IF(OR(K3="",K3=0),"",D3/K3) | T3: =IF(OR(S3="",S3=0),"",R3/S3) | U3: =Inputs!$B$4-A3 | V3: =IF(OR(G3="",U3<=0),"",MAX(0,Inputs!$B$1-G3)/U3)
A4: 3 | B4: =Inputs!$B$3+A4-1 | G4: =IF(C4="","",SUM($C$2:C4)-SUM($E$2:E4)) | H4: =IF(D4="","",SUM($D$2:D4)-SUM($F$2:F4)) | I4: =IF(G4="","",G4/Inputs!$B$1) | J4: =IF(OR(H4="",H4=0),"",G4/H4) | L4: =IF(OR(K4="",K4=0),"",D4/K4) | T4: =IF(OR(S4="",S4=0),"",R4/S4) | U4: =Inputs!$B$4-A4 | V4: =IF(OR(G4="",U4<=0),"",MAX(0,Inputs!$B$1-G4)/U4)
A5: 4 | B5: =Inputs!$B$3+A5-1 | G5: =IF(C5="","",SUM($C$2:C5)-SUM($E$2:E5)) | H5: =IF(D5="","",SUM($D$2:D5)-SUM($F$2:F5)) | I5: =IF(G5="","",G5/Inputs!$B$1) | J5: =IF(OR(H5="",H5=0),"",G5/H5) | L5: =IF(OR(K5="",K5=0),"",D5/K5) | T5: =IF(OR(S5="",S5=0),"",R5/S5) | U5: =Inputs!$B$4-A5 | V5: =IF(OR(G5="",U5<=0),"",MAX(0,Inputs!$B$1-G5)/U5)
A6: 5 | B6: =Inputs!$B$3+A6-1 | G6: =IF(C6="","",SUM($C$2:C6)-SUM($E$2:E6)) | H6: =IF(D6="","",SUM($D$2:D6)-SUM($F$2:F6)) | I6: =IF(G6="","",G6/Inputs!$B$1) | J6: =IF(OR(H6="",H6=0),"",G6/H6) | L6: =IF(OR(K6="",K6=0),"",D6/K6) | T6: =IF(OR(S6="",S6=0),"",R6/S6) | U6: =Inputs!$B$4-A6 | V6: =IF(OR(G6="",U6<=0),"",MAX(0,Inputs!$B$1-G6)/U6)
A7: 6 | B7: =Inputs!$B$3+A7-1 | G7: =IF(C7="","",SUM($C$2:C7)-SUM($E$2:E7)) | H7: =IF(D7="","",SUM($D$2:D7)-SUM($F$2:F7)) | I7: =IF(G7="","",G7/Inputs!$B$1) | J7: =IF(OR(H7="",H7=0),"",G7/H7) | L7: =IF(OR(K7="",K7=0),"",D7/K7) | T7: =IF(OR(S7="",S7=0),"",R7/S7) | U7: =Inputs!$B$4-A7 | V7: =IF(OR(G7="",U7<=0),"",MAX(0,Inputs!$B$1-G7)/U7)
A8: 7 | B8: =Inputs!$B$3+A8-1 | G8: =IF(C8="","",SUM($C$2:C8)-SUM($E$2:E8)) | H8: =IF(D8="","",SUM($D$2:D8)-SUM($F$2:F8)) | I8: =IF(G8="","",G8/Inputs!$B$1) | J8: =IF(OR(H8="",H8=0),"",G8/H8) | L8: =IF(OR(K8="",K8=0),"",D8/K8) | T8: =IF(OR(S8="",S8=0),"",R8/S8) | U8: =Inputs!$B$4-A8 | V8: =IF(OR(G8="",U8<=0),"",MAX(0,Inputs!$B$1-G8)/U8)
A9: 8 | B9: =Inputs!$B$3+A9-1 | G9: =IF(C9="","",SUM($C$2:C9)-SUM($E$2:E9)) | H9: =IF(D9="","",SUM($D$2:D9)-SUM($F$2:F9)) | I9: =IF(G9="","",G9/Inputs!$B$1) | J9: =IF(OR(H9="",H9=0),"",G9/H9) | L9: =IF(OR(K9="",K9=0),"",D9/K9) | T9: =IF(OR(S9="",S9=0),"",R9/S9) | U9: =Inputs!$B$4-A9 | V9: =IF(OR(G9="",U9<=0),"",MAX(0,Inputs!$B$1-G9)/U9)
A10: 9 | B10: =Inputs!$B$3+A10-1 | G10: =IF(C10="","",SUM($C$2:C10)-SUM($E$2:E10)) | H10: =IF(D10="","",SUM($D$2:D10)-SUM($F$2:F10)) | I10: =IF(G10="","",G10/Inputs!$B$1) | J10: =IF(OR(H10="",H10=0),"",G10/H10) | L10: =IF(OR(K10="",K10=0),"",D10/K10) | T10: =IF(OR(S10="",S10=0),"",R10/S10) | U10: =Inputs!$B$4-A10 | V10: =IF(OR(G10="",U10<=0),"",MAX(0,Inputs!$B$1-G10)/U10)
A11: 10 | B11: =Inputs!$B$3+A11-1 | G11: =IF(C11="","",SUM($C$2:C11)-SUM($E$2:E11)) | H11: =IF(D11="","",SUM($D$2:D11)-SUM($F$2:F11)) | I11: =IF(G11="","",G11/Inputs!$B$1) | J11: =IF(OR(H11="",H11=0),"",G11/H11) | L11: =IF(OR(K11="",K11=0),"",D11/K11) | T11: =IF(OR(S11="",S11=0),"",R11/S11) | U11: =Inputs!$B$4-A11 | V11: =IF(OR(G11="",U11<=0),"",MAX(0,Inputs!$B$1-G11)/U11)
A12: 11 | B12: =Inputs!$B$3+A12-1 | G12: =IF(C12="","",SUM($C$2:C12)-SUM($E$2:E12)) | H12: =IF(D12="","",SUM($D$2:D12)-SUM($F$2:F12)) | I12: =IF(G12="","",G12/Inputs!$B$1) | J12: =IF(OR(H12="",H12=0),"",G12/H12) | L12: =IF(OR(K12="",K12=0),"",D12/K12) | T12: =IF(OR(S12="",S12=0),"",R12/S12) | U12: =Inputs!$B$4-A12 | V12: =IF(OR(G12="",U12<=0),"",MAX(0,Inputs!$B$1-G12)/U12)
A13: 12 | B13: =Inputs!$B$3+A13-1 | G13: =IF(C13="","",SUM($C$2:C13)-SUM($E$2:E13)) | H13: =IF(D13="","",SUM($D$2:D13)-SUM($F$2:F13)) | I13: =IF(G13="","",G13/Inputs!$B$1) | J13: =IF(OR(H13="",H13=0),"",G13/H13) | L13: =IF(OR(K13="",K13=0),"",D13/K13) | T13: =IF(OR(S13="",S13=0),"",R13/S13) | U13: =Inputs!$B$4-A13 | V13: =IF(OR(G13="",U13<=0),"",MAX(0,Inputs!$B$1-G13)/U13)
A14: 13 | B14: =Inputs!$B$3+A14-1 | G14: =IF(C14="","",SUM($C$2:C14)-SUM($E$2:E14)) | H14: =IF(D14="","",SUM($D$2:D14)-SUM($F$2:F14)) | I14: =IF(G14="","",G14/Inputs!$B$1) | J14: =IF(OR(H14="",H14=0),"",G14/H14) | L14: =IF(OR(K14="",K14=0),"",D14/K14) | T14: =IF(OR(S14="",S14=0),"",R14/S14) | U14: =Inputs!$B$4-A14 | V14: =IF(OR(G14="",U14<=0),"",MAX(0,Inputs!$B$1-G14)/U14)
... A31: 30 | B31: =Inputs!$B$3+A31-1 | G31: =IF(C31="","",SUM($C$2:C31)-SUM($E$2:E31)) | H31: =IF(D31="","",SUM($D$2:D31)-SUM($F$2:F31)) | I31: =IF(G31="","",G31/Inputs!$B$1) | J31: =IF(OR(H31="",H31=0),"",G31/H31) | L31: =IF(OR(K31="",K31=0),"",D31/K31) | T31: =IF(OR(S31="",S31=0),"",R31/S31) | U31: =Inputs!$B$4-A31 | V31: =IF(OR(G31="",U31<=0),"",MAX(0,Inputs!$B$1-G31)/U31)

Sheet Tiers
A1: Tier | B1: Price | C1: Planned mix | D1: Backers (type from KS dashboard) | E1: Pledged | F1: Actual mix | G1: vs plan (points) | H1: Limit | I1: Remaining
A2: Ripple | B2: 5 | C2: 0.07 | D2: 0 | E2: =B2*D2 | F2: =IF(SUM($D$2:$D$9)=0,"",D2/SUM($D$2:$D$9)) | G2: =IF(F2="","",(F2-C2)*100)
A3: Early Diver | B3: 12 | C3: 0.18 | D3: 0 | E3: =B3*D3 | F3: =IF(SUM($D$2:$D$9)=0,"",D3/SUM($D$2:$D$9)) | G3: =IF(F3="","",(F3-C3)*100) | H3: 300 | I3: =H3-D3
A4: Diver | B4: 15 | C4: 0.2 | D4: 0 | E4: =B4*D4 | F4: =IF(SUM($D$2:$D$9)=0,"",D4/SUM($D$2:$D$9)) | G4: =IF(F4="","",(F4-C4)*100)
A5: Founding Diver | B5: 29 | C5: 0.22 | D5: 0 | E5: =B5*D5 | F5: =IF(SUM($D$2:$D$9)=0,"",D5/SUM($D$2:$D$9)) | G5: =IF(F5="","",(F5-C5)*100)
A6: Pod of Four | B6: 49 | C6: 0.2 | D6: 0 | E6: =B6*D6 | F6: =IF(SUM($D$2:$D$9)=0,"",D6/SUM($D$2:$D$9)) | G6: =IF(F6="","",(F6-C6)*100)
A7: Founding Pod | B7: 99 | C7: 0.1 | D7: 0 | E7: =B7*D7 | F7: =IF(SUM($D$2:$D$9)=0,"",D7/SUM($D$2:$D$9)) | G7: =IF(F7="","",(F7-C7)*100)
A8: Name the Trawler | B8: 199 | C8: 0.03 | D8: 0 | E8: =B8*D8 | F8: =IF(SUM($D$2:$D$9)=0,"",D8/SUM($D$2:$D$9)) | G8: =IF(F8="","",(F8-C8)*100) | H8: 25 | I8: =H8-D8
A9: No reward / custom | B9: 1 | C9: 0 | D9: 0 | E9: =B9*D9 | F9: =IF(SUM($D$2:$D$9)=0,"",D9/SUM($D$2:$D$9)) | G9: =IF(F9="","",(F9-C9)*100)
A11: Totals | D11: =SUM(D2:D9) | E11: =SUM(E2:E9)

Sheet Forecast
A1: Day | B1: Conservative: cumulative share of final total by this day | C1: Baseline | D1: Optimistic | E1: Forecast final (conservative) | F1: Forecast final (baseline) | G1: Forecast final (optimistic) | I1: Latest forecast
A2: 1 | B2: 0.1661 | C2: 0.1246 | D2: 0.0914 | E2: =IF(Daily!G2="","",Daily!G2/B2) | F2: =IF(Daily!G2="","",Daily!G2/C2) | G2: =IF(Daily!G2="","",Daily!G2/D2) | I2: Last filled day | J2: =COUNT(Daily!G2:G31)
A3: 2 | B3: 0.2892 | C3: 0.2169 | D3: 0.1591 | E3: =IF(Daily!G3="","",Daily!G3/B3) | F3: =IF(Daily!G3="","",Daily!G3/C3) | G3: =IF(Daily!G3="","",Daily!G3/D3) | I3: Conservative final pledged | J3: =IF($J$2=0,"",INDEX(E2:E31,$J$2)) | K3: =IF($J$2=0,"",INDEX(E2:E31,$J$2)/Inputs!$B$1)
A4: 3 | B4: 0.4 | C4: 0.3 | D4: 0.22 | E4: =IF(Daily!G4="","",Daily!G4/B4) | F4: =IF(Daily!G4="","",Daily!G4/C4) | G4: =IF(Daily!G4="","",Daily!G4/D4) | I4: Baseline final pledged | J4: =IF($J$2=0,"",INDEX(F2:F31,$J$2)) | K4: =IF($J$2=0,"",INDEX(F2:F31,$J$2)/Inputs!$B$1)
A5: 4 | B5: 0.4188 | C5: 0.32 | D5: 0.24 | E5: =IF(Daily!G5="","",Daily!G5/B5) | F5: =IF(Daily!G5="","",Daily!G5/C5) | G5: =IF(Daily!G5="","",Daily!G5/D5) | I5: Optimistic final pledged | J5: =IF($J$2=0,"",INDEX(G2:G31,$J$2)) | K5: =IF($J$2=0,"",INDEX(G2:G31,$J$2)/Inputs!$B$1)
A6: 5 | B6: 0.4375 | C6: 0.34 | D6: 0.26 | E6: =IF(Daily!G6="","",Daily!G6/B6) | F6: =IF(Daily!G6="","",Daily!G6/C6) | G6: =IF(Daily!G6="","",Daily!G6/D6)
A7: 6 | B7: 0.4563 | C7: 0.36 | D7: 0.28 | E7: =IF(Daily!G7="","",Daily!G7/B7) | F7: =IF(Daily!G7="","",Daily!G7/C7) | G7: =IF(Daily!G7="","",Daily!G7/D7) | I7: Curves are assumptions (yellow = the day-3 anchor). Forecasts before day 4 swing wildly; triggers T3/T7 wait for day 4.
A8: 7 | B8: 0.475 | C8: 0.38 | D8: 0.3 | E8: =IF(Daily!G8="","",Daily!G8/B8) | F8: =IF(Daily!G8="","",Daily!G8/C8) | G8: =IF(Daily!G8="","",Daily!G8/D8)
A9: 8 | B9: 0.4938 | C9: 0.4 | D9: 0.32 | E9: =IF(Daily!G9="","",Daily!G9/B9) | F9: =IF(Daily!G9="","",Daily!G9/C9) | G9: =IF(Daily!G9="","",Daily!G9/D9)
A10: 9 | B10: 0.5125 | C10: 0.42 | D10: 0.34 | E10: =IF(Daily!G10="","",Daily!G10/B10) | F10: =IF(Daily!G10="","",Daily!G10/C10) | G10: =IF(Daily!G10="","",Daily!G10/D10)
A11: 10 | B11: 0.5312 | C11: 0.44 | D11: 0.36 | E11: =IF(Daily!G11="","",Daily!G11/B11) | F11: =IF(Daily!G11="","",Daily!G11/C11) | G11: =IF(Daily!G11="","",Daily!G11/D11)
A12: 11 | B12: 0.55 | C12: 0.46 | D12: 0.38 | E12: =IF(Daily!G12="","",Daily!G12/B12) | F12: =IF(Daily!G12="","",Daily!G12/C12) | G12: =IF(Daily!G12="","",Daily!G12/D12)
A13: 12 | B13: 0.5687 | C13: 0.48 | D13: 0.4 | E13: =IF(Daily!G13="","",Daily!G13/B13) | F13: =IF(Daily!G13="","",Daily!G13/C13) | G13: =IF(Daily!G13="","",Daily!G13/D13)
A14: 13 | B14: 0.5875 | C14: 0.5 | D14: 0.42 | E14: =IF(Daily!G14="","",Daily!G14/B14) | F14: =IF(Daily!G14="","",Daily!G14/C14) | G14: =IF(Daily!G14="","",Daily!G14/D14)
A15: 14 | B15: 0.6062 | C15: 0.52 | D15: 0.44 | E15: =IF(Daily!G15="","",Daily!G15/B15) | F15: =IF(Daily!G15="","",Daily!G15/C15) | G15: =IF(Daily!G15="","",Daily!G15/D15)
A16: 15 | B16: 0.625 | C16: 0.54 | D16: 0.46 | E16: =IF(Daily!G16="","",Daily!G16/B16) | F16: =IF(Daily!G16="","",Daily!G16/C16) | G16: =IF(Daily!G16="","",Daily!G16/D16)
A17: 16 | B17: 0.6438 | C17: 0.56 | D17: 0.48 | E17: =IF(Daily!G17="","",Daily!G17/B17) | F17: =IF(Daily!G17="","",Daily!G17/C17) | G17: =IF(Daily!G17="","",Daily!G17/D17)
A18: 17 | B18: 0.6625 | C18: 0.58 | D18: 0.5 | E18: =IF(Daily!G18="","",Daily!G18/B18) | F18: =IF(Daily!G18="","",Daily!G18/C18) | G18: =IF(Daily!G18="","",Daily!G18/D18)
A19: 18 | B19: 0.6812 | C19: 0.6 | D19: 0.52 | E19: =IF(Daily!G19="","",Daily!G19/B19) | F19: =IF(Daily!G19="","",Daily!G19/C19) | G19: =IF(Daily!G19="","",Daily!G19/D19)
... A31: 30 | B31: 1 | C31: 1 | D31: 1 | E31: =IF(Daily!G31="","",Daily!G31/B31) | F31: =IF(Daily!G31="","",Daily!G31/C31) | G31: =IF(Daily!G31="","",Daily!G31/D31)

Sheet Triggers
A1: # | B1: Trigger | C1: Value now | D1: Threshold | E1: Fired? | F1: Response (11 §4)
A2: T1 | B2: Pre-launch: expected launch backers cover < 30% of goal (latest pre-launch row) | C2: =IF(COUNT('Pre-launch'!G2:G43)=0,"",INDEX('Pre-launch'!G2:G43,COUNT('Pre-launch'!G2:G43))) | D2: 0.3 | E2: =IF(C2="","—",IF(C2<D2,"FIRED","ok")) | F2: Weak pre-launch: postpone launch (11 §4.1)
A3: T2 | B3: Funded % at end of day 2 below 20% | C3: =IF(Daily!I3="","",Daily!I3) | D3: 0.2 | E3: =IF(C3="","—",IF(C3<D3,"FIRED","ok")) | F3: Slow first 48 h (11 §4.2)
A4: T3 | B4: Baseline forecast below 100% of goal (from day 4) | C4: =IF(OR(Forecast!J2<4,Forecast!K4=""),"",Forecast!K4) | D4: 1 | E4: =IF(C4="","—",IF(C4<D4,"FIRED","ok")) | F4: Funding below expectations (11 §4.5)
A5: T4 | B5: Pledged today < 50% of needed-per-day for 3 days running (latest 3 filled days) | C5: =IF(Forecast!J2<4,"",IF(AND(INDEX(Daily!C2:C31,Forecast!J2)<0.5*INDEX(Daily!V2:V31,Forecast!J2-1),INDEX(Daily!C2:C31,Forecast!J2-1)<0.5*INDEX(Daily!V2:V31,Forecast!J2-2),INDEX(Daily!C2:C31,Forecast!J2-2)<0.5*INDEX(Daily!V2:V31,Forecast!J2-3)),1,0)) | D5: 1 | E5: =IF(C5="","—",IF(C5=D5,"FIRED","ok")) | F5: Mid-campaign plateau (11 §4.3)
A6: T5 | B6: Cancellations above threshold (% of gross pledged) | C6: =IF(SUM(Daily!C2:C31)=0,"",SUM(Daily!E2:E31)/SUM(Daily!C2:C31)) | D6: =Inputs!B8 | E6: =IF(C6="","—",IF(C6>D6,"FIRED","ok")) | F6: Investigate: price, a bad update, card failures
A7: T6 | B7: Ad cost per backer above net revenue per backer | C7: =IF(SUM(Daily!S2:S31)=0,"",SUM(Daily!R2:R31)/SUM(Daily!S2:S31)) | D7: =Inputs!B6 | E7: =IF(C7="","—",IF(C7>D7,"FIRED","ok")) | F7: Pause the ads (11 §4)
A8: T7 | B8: Optimistic forecast above 300% of goal (from day 4) | C8: =IF(OR(Forecast!J2<4,Forecast!K5=""),"",Forecast!K5) | D8: 3 | E8: =IF(C8="","—",IF(C8>D8,"FIRED","ok")) | F8: Sudden attention (11 §4.4)
A9: T8 | B9: A limited tier sold out (remaining = 0) | C9: =IF(OR(Tiers!I3=0,Tiers!I8=0),1,0) | D9: 1 | E9: =IF(C9="","—",IF(C9=D9,"FIRED","ok")) | F9: Say so once in an update; do NOT add another limited tier
